pytranskit/__init__.py
pytranskit/TBM/TBM_CLOT.py
pytranskit/TBM/TBM_PLOT.py
pytranskit/TBM/TBM_RCDT.py
pytranskit/TBM/__init__.py
pytranskit/TBM/preprocessing.py
pytranskit/TBM/utils.py
pytranskit/classification/RSCDT_NS.py
pytranskit/classification/__init__.py
pytranskit/classification/cdt_ns.py
pytranskit/classification/inv_enc.py
pytranskit/classification/rcdt_ns.py
pytranskit/classification/rcdt_ns_3d.py
pytranskit/classification/scdt_nls.py
pytranskit/classification/scdt_ns.py
pytranskit/classification/utils.py
pytranskit/optrans/__init__.py
pytranskit/optrans/continuous/__init__.py
pytranskit/optrans/continuous/base.py
pytranskit/optrans/continuous/cdt.py
pytranskit/optrans/continuous/clot.py
pytranskit/optrans/continuous/radoncdt.py
pytranskit/optrans/continuous/radoncdt3D.py
pytranskit/optrans/continuous/radonscdt.py
pytranskit/optrans/continuous/scdt.py
pytranskit/optrans/decomposition/__init__.py
pytranskit/optrans/decomposition/cca.py
pytranskit/optrans/decomposition/modes.py
pytranskit/optrans/decomposition/plda.py
pytranskit/optrans/utils/__init__.py
pytranskit/optrans/utils/data_utils.py
pytranskit/optrans/utils/validation.py
pytranskit/optrans/utils/visualize.py
pytranskit/optrans/visualization/__init__.py
pytranskit/optrans/visualization/visualize.py
pytranskit-0.2.9.dist-info/LICENSE
pytranskit-0.2.9.dist-info/METADATA
pytranskit-0.2.9.dist-info/WHEEL
pytranskit-0.2.9.dist-info/top_level.txt
pytranskit-0.2.9.dist-info/RECORD
