Metadata-Version: 2.1
Name: pytranskit
Version: 0.2.9
Summary: Python transport based signal processing toolkit.
Home-page: https://github.com/rohdelab/PyTransKit
Author: Abu Hasnat Mohammad Rubaiyat, Xuwang Yin, Liam Cattell, Soheil Kolouri, Mohammad Shifat-E-Rabbi, Yan Zhuang, Gustavo Rohde
Author-email: ar3fx@virginia.edu, xuwangyin@gmail.com, gustavo.rohde@gmail.com
Classifier: Development Status :: 3 - Alpha
Classifier: Intended Audience :: Developers
Classifier: Intended Audience :: Science/Research
Classifier: Topic :: Scientific/Engineering
Classifier: License :: OSI Approved :: GNU General Public License v3 (GPLv3)
Classifier: Programming Language :: Python :: 3
Classifier: Programming Language :: Python :: 3.4
Classifier: Programming Language :: Python :: 3.5
Classifier: Programming Language :: Python :: 3.6
Requires-Python: >=3.6
License-File: LICENSE
